sensorbucket/__init__.py
sensorbucket/api_client.py
sensorbucket/api_response.py
sensorbucket/configuration.py
sensorbucket/exceptions.py
sensorbucket/py.typed
sensorbucket/rest.py
sensorbucket/api/__init__.py
sensorbucket/api/api_keys_api.py
sensorbucket/api/devices_api.py
sensorbucket/api/measurements_api.py
sensorbucket/api/pipelines_api.py
sensorbucket/api/tenants_api.py
sensorbucket/api/tracing_api.py
sensorbucket/api/uplink_api.py
sensorbucket/api/workers_api.py
sensorbucket/models/__init__.py
sensorbucket/models/add_sensor_to_sensor_group201_response.py
sensorbucket/models/add_sensor_to_sensor_group_request.py
sensorbucket/models/add_tenant_member201_response.py
sensorbucket/models/add_tenant_member_request.py
sensorbucket/models/api_error.py
sensorbucket/models/api_key.py
sensorbucket/models/api_key_created.py
sensorbucket/models/archived_ingress.py
sensorbucket/models/create_api_key_request.py
sensorbucket/models/create_device201_response.py
sensorbucket/models/create_device_request.py
sensorbucket/models/create_device_sensor201_response.py
sensorbucket/models/create_pipeline200_response.py
sensorbucket/models/create_pipeline_request.py
sensorbucket/models/create_sensor_group201_response.py
sensorbucket/models/create_sensor_group_request.py
sensorbucket/models/create_sensor_request.py
sensorbucket/models/create_user_worker_request.py
sensorbucket/models/create_worker201_response.py
sensorbucket/models/datastream.py
sensorbucket/models/delete_device200_response.py
sensorbucket/models/delete_device_sensor200_response.py
sensorbucket/models/delete_sensor_from_sensor_group200_response.py
sensorbucket/models/delete_sensor_group200_response.py
sensorbucket/models/device.py
sensorbucket/models/disable_pipeline200_response.py
sensorbucket/models/get_datastream200_response.py
sensorbucket/models/get_datastream200_response_data.py
sensorbucket/models/get_device200_response.py
sensorbucket/models/get_pipeline200_response.py
sensorbucket-1.2.5.dist-info/METADATA
sensorbucket-1.2.5.dist-info/WHEEL
sensorbucket-1.2.5.dist-info/top_level.txt
sensorbucket-1.2.5.dist-info/RECORD
