Metadata-Version: 2.1
Name: sensorbucket
Version: 1.2.5
Summary: Sensorbucket API
Home-page: https://sensorbucket.nl
Author: Tim van Osch
Author-email: info@pollex.nl
License: EUPLv1.2
Keywords: OpenAPI,OpenAPI-Generator,Sensorbucket API
Requires-Dist: urllib3 <2.1.0,>=1.25.3
Requires-Dist: python-dateutil
Requires-Dist: pydantic >=2
Requires-Dist: typing-extensions >=4.7.1
